revolt/__init__.py
revolt/_substitutor.py
revolt/_validator.py
revolt/_version.py
revolt/py.typed
revolt/errors/__init__.py
tests/types/__init__.py
tests/types/alias/__init__.py
tests/types/alias/test_alias_substitution.py
tests/types/any/__init__.py
tests/types/any/test_any_substitution.py
tests/types/bool/__init__.py
tests/types/bool/test_bool_substitution.py
tests/types/bytes/__init__.py
tests/types/bytes/test_bytes_substitution.py
tests/types/const/__init__.py
tests/types/const/test_const_substitution.py
tests/types/date_type/__init__.py
tests/types/date_type/test_date_substitution.py
tests/types/datetime_type/__init__.py
tests/types/datetime_type/test_datetime_substitution.py
tests/types/dict/__init__.py
tests/types/dict/test_dict_relaxed_substitution.py
tests/types/dict/test_dict_substitution.py
tests/types/float/__init__.py
tests/types/float/test_float_substitution.py
tests/types/int/__init__.py
tests/types/int/test_int_substitution.py
tests/types/list/__init__.py
tests/types/list/test_list_contains_substitution.py
tests/types/list/test_list_of_substitution.py
tests/types/list/test_list_substitution.py
tests/types/none/__init__.py
tests/types/none/test_none_substitution.py
tests/types/str/__init__.py
tests/types/str/test_str_substitution.py
tests/types/uuid4/__init__.py
tests/types/uuid4/test_uuid4_substitution.py
revolt-1.9.0.dist-info/LICENSE.txt
revolt-1.9.0.dist-info/METADATA
revolt-1.9.0.dist-info/WHEEL
revolt-1.9.0.dist-info/top_level.txt
revolt-1.9.0.dist-info/RECORD
